<?xml version="1.0" encoding="utf-8"?>
<Defs>
	<ThingDef Abstract="True" Name="ZP_BuildingBase">
		<category>Building</category>
		<thingClass>Building</thingClass>
		<soundImpactDefault>BulletImpactMetal</soundImpactDefault>
		<selectable>true</selectable>
		<drawerType>MapMeshAndRealTime</drawerType>
		<terrainAffordanceNeeded>Light</terrainAffordanceNeeded>
		<repairEffect>Repair</repairEffect>
		<leaveResourcesWhenKilled>true</leaveResourcesWhenKilled>
		<filthLeaving>BuildingRubble</filthLeaving>
		<statBases>
			<SellPriceFactor>0.70</SellPriceFactor>
		</statBases>
		<designationCategory>Zipangu</designationCategory>
	</ThingDef>
	<ThingDef Name="Rice_BuildingBase" ParentName="ZP_BuildingBase" Abstract="True">
		<castEdgeShadows>false</castEdgeShadows>
		<surfaceType>Item</surfaceType>
		<hasInteractionCell>true</hasInteractionCell>
		<interactionCellOffset>(0,0,-1)</interactionCellOffset>
		<terrainAffordanceNeeded>Light</terrainAffordanceNeeded>
		<altitudeLayer>Building</altitudeLayer>
		<fillPercent>0.5</fillPercent>
		<useHitPoints>true</useHitPoints>
		<passability>PassThroughOnly</passability>
		<minifiedDef>MinifiedFurniture</minifiedDef>
		<graphicData>
			<shaderType>CutoutComplex</shaderType>
			<damageData>
				<cornerTL>Damage/Corner</cornerTL>
				<cornerTR>Damage/Corner</cornerTR>
				<cornerBL>Damage/Corner</cornerBL>
				<cornerBR>Damage/Corner</cornerBR>
			</damageData>
		</graphicData>
		<building>
			<workSpeedPenaltyOutdoors>false</workSpeedPenaltyOutdoors>
			<workSpeedPenaltyTemperature>true</workSpeedPenaltyTemperature>
			<spawnedConceptLearnOpportunity>BillsTab</spawnedConceptLearnOpportunity>
		</building>
		<statBases>
			<MaxHitPoints>250</MaxHitPoints>
			<Flammability>1.0</Flammability>
			<SellPriceFactor>0.70</SellPriceFactor>
		</statBases>
		<comps>
			<li>
				<compClass>CompReportWorkSpeed</compClass>
			</li>
		</comps>
		<placeWorkers>
			<li>PlaceWorker_ReportWorkSpeedPenalties</li>
		</placeWorkers>
		<inspectorTabs>
			<li>ITab_Bills</li>
		</inspectorTabs>
	</ThingDef>
	<ThingDef Abstract="True" ParentName="ZP_BuildingBase" Name="PicnicBase">
		<altitudeLayer>Building</altitudeLayer>
		<passability>Standable</passability>
		<castEdgeShadows>true</castEdgeShadows>
		<tradeability>Never</tradeability>
		<pathCost>60</pathCost>
		<fillPercent>0.5</fillPercent>
		<resourcesFractionWhenDeconstructed>1</resourcesFractionWhenDeconstructed>
		<socialPropernessMatters>true</socialPropernessMatters>
		<leaveResourcesWhenKilled>true</leaveResourcesWhenKilled>
		<staticSunShadowHeight>0.20</staticSunShadowHeight>
		<surfaceType>Eat</surfaceType>
		<comps>
			<li>
				<compClass>CompGatherSpot</compClass>
			</li>
			<li Class="CompProperties_RoomIdentifier">
				<roomStat>Impressiveness</roomStat>
			</li>
		</comps>
	</ThingDef>
</Defs>
