<?xml version="1.0" encoding="utf-8"?>
<Defs>
	<ThingDef ParentName="ZPMealRottable">
		<defName>BR_Gohan</defName>
		<label>ご飯(玄米)</label>
		<description>オカズが欲しいなんて言わずにお米そのままの味を楽しもう!!</description>
		<graphicData>
			<texPath>Things/Item/Food/genmaigohan</texPath>
			<graphicClass>Graphic_Single</graphicClass>
		</graphicData>
		<statBases>
			<MarketValue>20</MarketValue>
			<WorkToMake>300</WorkToMake>
		</statBases>
		<ingestible>
			<preferability>MealSimple</preferability>
			<nutrition>1.0</nutrition>
		</ingestible>
	</ThingDef>
	<ThingDef ParentName="ZPMealRottable">
		<defName>WR_Gohan</defName>
		<label>ご飯</label>
		<description>白米をじっくりと楽しむためにお椀によそられた最高の1杯</description>
		<graphicData>
			<texPath>Things/Item/Food/gohan</texPath>
			<graphicClass>Graphic_Single</graphicClass>
		</graphicData>
		<statBases>
			<MarketValue>25</MarketValue>
			<WorkToMake>300</WorkToMake>
		</statBases>
		<ingestible>
			<preferability>MealSimple</preferability>
			<tasteThought>R_AteMealSimple</tasteThought>
			<nutrition>0.90</nutrition>
		</ingestible>
	</ThingDef>
	<ThingDef ParentName="ZPMealRottable">
		<defName>BR_TKG</defName>
		<label>玄米 卵かけご飯</label>
		<description>ご飯のままでも美味しいのに生卵をのせるという悪魔の所業の一品。</description>
		<graphicData>
			<texPath>Things/Item/Food/tamagogenmai</texPath>
			<graphicClass>Graphic_Single</graphicClass>
		</graphicData>
		<statBases>
			<MarketValue>20</MarketValue>
			<WorkToMake>300</WorkToMake>
		</statBases>
		<ingestible>
			<preferability>MealFine</preferability>
			<tasteThought>AteFineMeal</tasteThought>
			<nutrition>1.0</nutrition>
		</ingestible>
	</ThingDef>
	<ThingDef ParentName="ZPMealRottable">
		<defName>WR_TKG</defName>
		<label>卵かけご飯</label>
		<description>ご飯のままでも美味しいのに生卵をのせるという悪魔の所業の一品。</description>
		<graphicData>
			<texPath>Things/Item/Food/tamagogohan</texPath>
			<graphicClass>Graphic_Single</graphicClass>
		</graphicData>
		<statBases>
			<MarketValue>25</MarketValue>
			<WorkToMake>300</WorkToMake>
		</statBases>
		<ingestible>
			<preferability>MealFine</preferability>
			<tasteThought>R_AteMealFine</tasteThought>
			<nutrition>0.90</nutrition>
		</ingestible>
	</ThingDef>
	<ThingDef ParentName="ZPMealRottable">
		<defName>BR_Onigiri</defName>
		<label>おにぎり(玄米)</label>
		<description>どこでも食べれる塩味のきいたおにぎり</description>
		<graphicData>
			<texPath>Things/Item/Food/onigiri_g</texPath>
			<graphicClass>Graphic_single</graphicClass>
		</graphicData>
		<statBases>
			<MarketValue>20</MarketValue>
			<WorkToMake>250</WorkToMake>
		</statBases>
		<ingestible>
			<preferability>MealSimple</preferability>
			<nutrition>0.9</nutrition>
			<chairSearchRadius>9</chairSearchRadius>
		</ingestible>
	</ThingDef>
	<ThingDef ParentName="ZPMealRottable">
		<defName>WR_Onigiri</defName>
		<label>おにぎり</label>
		<description>どこでも食べれる塩味のきいた白米のおにぎり</description>
		<graphicData>
			<texPath>Things/Item/Food/onigiri</texPath>
			<graphicClass>Graphic_single</graphicClass>
		</graphicData>
		<statBases>
			<MarketValue>30</MarketValue>
			<WorkToMake>250</WorkToMake>
		</statBases>
		<ingestible>
			<preferability>MealSimple</preferability>
			<tasteThought>R_AteMealSimple</tasteThought>
			<nutrition>0.8</nutrition>
			<chairSearchRadius>9</chairSearchRadius>
		</ingestible>
	</ThingDef>
	<ThingDef ParentName="ZPMealRottable">
		<defName>BR_Bento</defName>
		<label>日の丸弁当(玄米)</label>
		<description>どこでも食べれるお弁当。</description>
		<graphicData>
			<texPath>Things/Item/Food/bentou_g</texPath>
			<graphicClass>Graphic_single</graphicClass>
		</graphicData>
		<statBases>
			<MarketValue>30</MarketValue>
			<WorkToMake>500</WorkToMake>
		</statBases>
		<ingestible>
			<preferability>MealFine</preferability>
			<tasteThought>AteFineMeal</tasteThought>
			<nutrition>1.0</nutrition>
			<chairSearchRadius>9</chairSearchRadius>
		</ingestible>
	</ThingDef>
	<ThingDef ParentName="ZPMealRottable">
		<defName>WR_Bento</defName>
		<label>日の丸弁当</label>
		<description>どこでも食べれる白米のお弁当。</description>
		<graphicData>
			<texPath>Things/Item/Food/bentou</texPath>
			<graphicClass>Graphic_single</graphicClass>
		</graphicData>
		<statBases>
			<MarketValue>40</MarketValue>
			<WorkToMake>500</WorkToMake>
		</statBases>
		<ingestible>
			<preferability>MealFine</preferability>
			<tasteThought>R_AteMealFine</tasteThought>
			<nutrition>0.9</nutrition>
			<chairSearchRadius>9</chairSearchRadius>
		</ingestible>
	</ThingDef>
	<ThingDef ParentName="ZPMealRottable">
		<defName>BR_Jubako</defName>
		<label>重箱(玄米)</label>
		<description>どこでも食べれる豪華なお弁当。</description>
		<graphicData>
			<texPath>Things/Item/Food/jubako_g</texPath>
			<graphicClass>Graphic_single</graphicClass>
		</graphicData>
		<statBases>
			<MarketValue>40</MarketValue>
			<WorkToMake>700</WorkToMake>
		</statBases>
		<ingestible>
			<preferability>MealLavish</preferability>
			<tasteThought>AteLavishMeal</tasteThought>
			<nutrition>1.2</nutrition>
			<joy>0.06</joy>
			<joyKind>Gluttonous</joyKind>
			<chairSearchRadius>9</chairSearchRadius>
		</ingestible>
	</ThingDef>
	<ThingDef ParentName="ZPMealRottable">
		<defName>WR_Jubako</defName>
		<label>重箱</label>
		<description>どこでも食べれる豪華で白米のお弁当。</description>
		<graphicData>
			<texPath>Things/Item/Food/jubako</texPath>
			<graphicClass>Graphic_single</graphicClass>
		</graphicData>
		<statBases>
			<MarketValue>50</MarketValue>
			<WorkToMake>700</WorkToMake>
		</statBases>
		<ingestible>
			<preferability>MealLavish</preferability>
			<tasteThought>R_MealLavish</tasteThought>
			<nutrition>1.00</nutrition>
			<joy>0.06</joy>
			<joyKind>Gluttonous</joyKind>
			<chairSearchRadius>9</chairSearchRadius>
		</ingestible>
	</ThingDef>
	<ThingDef ParentName="ZPMealRottable">
		<defName>BR_Gyudon</defName>
		<label>肉丼(玄米)</label>
		<description>ご飯の上にがっつり肉を盛り付けたどんぶり。</description>
		<graphicData>
			<texPath>Things/Item/Food/nikudon_g</texPath>
			<graphicClass>Graphic_Single</graphicClass>
		</graphicData>
		<statBases>
			<MarketValue>20</MarketValue>
			<WorkToMake>300</WorkToMake>
		</statBases>
		<ingestible>
			<preferability>MealFine</preferability>
			<tasteThought>AteFineMeal</tasteThought>
			<nutrition>1.2</nutrition>
		</ingestible>
	</ThingDef>
	<ThingDef ParentName="ZPMealRottable">
		<defName>WR_Gyudon</defName>
		<label>肉丼</label>
		<description>ご飯の上にがっつり肉を盛り付けた白米のどんぶり。</description>
		<graphicData>
			<texPath>Things/Item/Food/nikudon</texPath>
			<graphicClass>Graphic_Single</graphicClass>
		</graphicData>
		<statBases>
			<MarketValue>25</MarketValue>
			<WorkToMake>300</WorkToMake>
		</statBases>
		<ingestible>
			<preferability>MealFine</preferability>
			<tasteThought>R_AteMealFine</tasteThought>
			<nutrition>1.0</nutrition>
			<joy>0.04</joy>
			<joyKind>Gluttonous</joyKind>
		</ingestible>
	</ThingDef>
	<ThingDef ParentName="ZPMealRottable">
		<defName>WR_JPCurryRice</defName>
		<label>カレーライス</label>
		<description>とある国では食べ方や食材を何にするかで戦争が起きるほど、皆が愛してやまない魅惑のカレーライス。</description>
		<graphicData>
			<texPath>Things/Item/Food/CurryRice</texPath>
			<graphicClass>Graphic_single</graphicClass>
		</graphicData>
		<statBases>
			<MarketValue>80</MarketValue>
			<WorkToMake>800</WorkToMake>
		</statBases>
		<ingestible>
			<preferability>MealLavish</preferability>
			<tasteThought>R_CurryRice</tasteThought>
			<nutrition>1.20</nutrition>
			<joy>0.08</joy>
			<joyKind>Gluttonous</joyKind>
		</ingestible>
	</ThingDef>
	<ThingDef ParentName="ZPMealRottable">
		<defName>Tukudani</defName>
		<label>イナゴの佃煮</label>
		<description>普段は捨てられるはずの虫の肉を砂糖と醤油で甘辛く煮付けた食べ物。</description>
		<graphicData>
			<texPath>Things/Item/Food/tukudani</texPath>
			<graphicClass>Graphic_Single</graphicClass>
		</graphicData>
		<statBases>
			<MarketValue>18</MarketValue>
			<WorkToMake>300</WorkToMake>
		</statBases>
		<ingestible>
			<preferability>MealSimple</preferability>
			<optimalityOffsetHumanlikes>-5</optimalityOffsetHumanlikes>
			<tasteThought>R_AteTukudani</tasteThought>
			<nutrition>0.80</nutrition>
		</ingestible>
	</ThingDef>
	<ThingDef ParentName="ZPMealRottable">
		<defName>ZP_WRSushi</defName>
		<label>握り寿司</label>
		<description>酢飯の上に新鮮な魚の切り身をのせ握った伝統的な日本料理。</description>
		<graphicData>
			<texPath>Things/Item/Food/susi</texPath>
			<graphicClass>Graphic_Random</graphicClass>
		</graphicData>
		<statBases>
			<MarketValue>50</MarketValue>
			<WorkToMake>800</WorkToMake>
		</statBases>
		<ingestible>
			<preferability>MealLavish</preferability>
			<tasteThought>R_MealLavish</tasteThought>
			<nutrition>1.00</nutrition>
			<joy>0.1</joy>
			<joyKind>Gluttonous</joyKind>
			<outcomeDoers>
				<li Class="IngestionOutcomeDoer_GiveHediff">
					<hediffDef>HedFreshFishFood</hediffDef>
					<severity>0.5</severity>
				</li>
			</outcomeDoers>
		</ingestible>
		<comps>
			<li Class="CompProperties_Rottable">
				<daysToRotStart>2</daysToRotStart>
				<rotDestroys>true</rotDestroys>
			</li>
		</comps>
	</ThingDef>
	<ThingDef ParentName="ZPMealRottable">
		<defName>ZP_Sasimi</defName>
		<label>赤身の刺身</label>
		<description>新鮮な生魚を食べやすい大きさに切りお皿に盛り合わせたもの。</description>
		<graphicData>
			<texPath>Things/Item/Food/sasimi</texPath>
			<graphicClass>Graphic_Single</graphicClass>
		</graphicData>
		<statBases>
			<MarketValue>30</MarketValue>
			<WorkToMake>800</WorkToMake>
		</statBases>
		<ingestible>
			<preferability>MealFine</preferability>
			<tasteThought>AteFineMeal</tasteThought>
			<nutrition>0.8</nutrition>
			<joy>0.08</joy>
			<joyKind>Gluttonous</joyKind>
			<outcomeDoers>
				<li Class="IngestionOutcomeDoer_GiveHediff">
					<hediffDef>HedFreshFishFood</hediffDef>
					<severity>0.5</severity>
				</li>
			</outcomeDoers>
		</ingestible>
		<comps>
			<li Class="CompProperties_Rottable">
				<daysToRotStart>2</daysToRotStart>
				<rotDestroys>true</rotDestroys>
			</li>
		</comps>
	</ThingDef>
	<ThingDef ParentName="ZPMealRottable">
		<defName>ZP_SaltGrilledFish</defName>
		<label>魚の塩焼き</label>
		<description>塩をまぶした魚を串にさし直火で焼いたもの。焼いた魚の旨味を堪能できる一品。</description>
		<stackLimit>20</stackLimit>
		<graphicData>
			<texPath>Things/Item/Food/sioyaki</texPath>
			<graphicClass>Graphic_single</graphicClass>
		</graphicData>
		<statBases>
			<MarketValue>30</MarketValue>
			<WorkToMake>250</WorkToMake>
		</statBases>
		<ingestible>
			<preferability>MealFine</preferability>
			<tasteThought>AteFineMeal</tasteThought>
			<nutrition>0.8</nutrition>
			<joy>0.08</joy>
			<joyKind>Gluttonous</joyKind>
			<outcomeDoers>
				<li Class="IngestionOutcomeDoer_GiveHediff">
					<hediffDef>HedFishFood</hediffDef>
					<severity>0.5</severity>
				</li>
			</outcomeDoers>
		</ingestible>
	</ThingDef>
	<ThingDef ParentName="ZPMealRottable">
		<defName>ZP_SteamedFish</defName>
		<label>魚の煮付け</label>
		<description>魚を軽く茹でた後に調味料で味をつけ煮付けた食べ物。</description>
		<graphicData>
			<texPath>Things/Item/Food/nituke</texPath>
			<graphicClass>Graphic_Single</graphicClass>
		</graphicData>
		<statBases>
			<MarketValue>30</MarketValue>
			<WorkToMake>800</WorkToMake>
		</statBases>
		<ingestible>
			<preferability>MealFine</preferability>
			<tasteThought>AteFineMeal</tasteThought>
			<nutrition>0.9</nutrition>
			<joy>0.04</joy>
			<joyKind>Gluttonous</joyKind>
			<outcomeDoers>
				<li Class="IngestionOutcomeDoer_GiveHediff">
					<hediffDef>HedFishFood</hediffDef>
					<severity>0.5</severity>
				</li>
			</outcomeDoers>
		</ingestible>
	</ThingDef>
</Defs>
