<?xml version="1.0" encoding="utf-8"?>
<Defs>
	<!-- ================ 十手 Base クラブ ================ -->
	<ThingDef ParentName="ZPMeleeWeapon">
		<defName>MeleeWeapon_Jitte</defName>
		<label>十手</label>
		<description>日本に古くから伝わる捕物道具。敵の攻撃を防ぐことができる。</description>
		<recipeMaker>
			<recipeUsers>
				<li>CraftingSpot</li>
				<li>ElectricSmithy</li>
				<li>FueledSmithy</li>
			</recipeUsers>
		</recipeMaker>
		<graphicData>
			<texPath>Things/Item/Equipment/WeaponMelee/zitte</texPath>
			<graphicClass>Graphic_Single</graphicClass>
		</graphicData>
		<statBases>
			<WorkToMake>1000</WorkToMake>
			<Mass>2</Mass>
			<Weapon_Bulk>0.5</Weapon_Bulk>
		</statBases>
		<equippedStatOffsets>
			<MeleeDodgeChance>3.0</MeleeDodgeChance>
		</equippedStatOffsets>
		<equippedAngleOffset>-65</equippedAngleOffset>
		<stuffCategories>
			<li>Metallic</li>
			<li>Woody</li>
		</stuffCategories>
		<costStuffCount>30</costStuffCount>
		<tools>
			<li>
				<label>handle</label>
				<capacities>
					<li>Poke</li>
				</capacities>
				<power>4</power>
				<cooldownTime>1.5</cooldownTime>
			</li>
			<li>
				<label>head</label>
				<capacities>
					<li>Blunt</li>
				</capacities>
				<power>6</power>
				<cooldownTime>1.5</cooldownTime>
			</li>
		</tools>
		<weaponTags>
			<li>ZP_Weapons_Asigaru</li>
		</weaponTags>
	</ThingDef>
	<!-- ================ 十手 Base クラブ ================ -->
	<ThingDef ParentName="ZPMeleeWeapon">
		<defName>MeleeWeapon_Marohoshi</defName>
		<label>まろほし</label>
		<description>十手を改造することで敵の攻撃を更に防ぎやすくなった捕物道具。</description>
		<recipeMaker>
			<researchPrerequisite>Smithing</researchPrerequisite>
			<recipeUsers>
				<li>ElectricSmithy</li>
				<li>FueledSmithy</li>
			</recipeUsers>
		</recipeMaker>
		<graphicData>
			<texPath>Things/Item/Equipment/WeaponMelee/marohosi</texPath>
			<graphicClass>Graphic_Single</graphicClass>
		</graphicData>
		<statBases>
			<WorkToMake>5000</WorkToMake>
			<Mass>2</Mass>
			<Weapon_Bulk>0.8</Weapon_Bulk>
		</statBases>
		<equippedStatOffsets>
			<MeleeDodgeChance>9.0</MeleeDodgeChance>
		</equippedStatOffsets>
		<equippedAngleOffset>-65</equippedAngleOffset>
		<stuffCategories>
			<li>Metallic</li>
			<li>Woody</li>
		</stuffCategories>
		<costStuffCount>60</costStuffCount>
		<tools>
			<li>
				<label>handle</label>
				<capacities>
					<li>Poke</li>
				</capacities>
				<power>4</power>
				<cooldownTime>2</cooldownTime>
			</li>
			<li>
				<label>head</label>
				<capacities>
					<li>Blunt</li>
				</capacities>
				<power>6</power>
				<cooldownTime>2</cooldownTime>
			</li>
		</tools>
		<weaponTags>
			<li>ZP_Weapons_Asigaru</li>
		</weaponTags>
	</ThingDef>
	<!-- ================ 十手 Base クラブ ================ -->
	<ThingDef ParentName="ZPMeleeWeapon">
		<defName>MeleeWeapon_Sasumata</defName>
		<label>刺叉</label>
		<description>相手の動きを封じ込むための捕物道具。近接相手は牽制できるが飛び道具相手には対応できない。</description>
		<recipeMaker>
			<researchPrerequisite>BlacksmithApprentice</researchPrerequisite>
			<skillRequirements>
				<Crafting>6</Crafting>
			</skillRequirements>
		</recipeMaker>
		<graphicData>
			<texPath>Things/Item/Equipment/WeaponMelee/sasumata</texPath>
			<graphicClass>Graphic_Single</graphicClass>
		</graphicData>
		<statBases>
			<WorkToMake>10000</WorkToMake>
			<Mass>2</Mass>
			<Weapon_Bulk>1.2</Weapon_Bulk>
		</statBases>
		<equippedStatOffsets>
			<MeleeDodgeChance>15</MeleeDodgeChance>
		</equippedStatOffsets>
		<equippedAngleOffset>-65</equippedAngleOffset>
		<stuffCategories>
			<li>Metallic</li>
			<li>Woody</li>
		</stuffCategories>
		<costStuffCount>100</costStuffCount>
		<tools>
			<li>
				<label>handle</label>
				<capacities>
					<li>Poke</li>
				</capacities>
				<power>4</power>
				<cooldownTime>2.5</cooldownTime>
			</li>
			<li>
				<label>head</label>
				<capacities>
					<li>Blunt</li>
				</capacities>
				<power>6</power>
				<cooldownTime>2.5</cooldownTime>
			</li>
		</tools>
		<weaponTags>
			<li>ZP_Weapons_Asigaru</li>
		</weaponTags>
	</ThingDef>
	<!-- ================ 脇差 Base グラディウス ================ -->
	<ThingDef ParentName="ZPMeleeWeapon">
		<defName>MeleeWeapon_Wakizasi</defName>
		<label>脇差</label>
		<description>It is a short sword handed down in the East.It is used as a spare weapon for when the main weapon is broken.</description>
		<graphicData>
			<texPath>Things/Item/Equipment/WeaponMelee/wakizasi</texPath>
			<graphicClass>Graphic_Single</graphicClass>
		</graphicData>
		<recipeMaker>
			<researchPrerequisite>Smithing</researchPrerequisite>
		</recipeMaker>
		<statBases>
			<WorkToMake>10000</WorkToMake>
			<Mass>0.85</Mass>
			<Weapon_Bulk>0.8</Weapon_Bulk>
		</statBases>
		<equippedAngleOffset>-65</equippedAngleOffset>
		<stuffCategories>
			<li>Metallic</li>
			<li>Woody</li>
		</stuffCategories>
		<costStuffCount>50</costStuffCount>
		<tools>
			<li>
				<label>突き</label>
				<capacities>
					<li>Stab</li>
				</capacities>
				<power>3</power>
				<cooldownTime>1.1</cooldownTime>
			</li>
			<li>
				<label>薙ぎ払い</label>
				<capacities>
					<li>Cut</li>
				</capacities>
				<power>5</power>
				<cooldownTime>1.1</cooldownTime>
			</li>
			<li>
				<label>振り下ろし</label>
				<capacities>
					<li>Cut</li>
				</capacities>
				<power>9</power>
				<cooldownTime>1.1</cooldownTime>
			</li>
		</tools>
		<weaponTags>
			<li>ZP_Weapons_Asigaru</li>
		</weaponTags>
	</ThingDef>
	<!-- ================ 刀 Base ロングソード ================ -->
	<ThingDef ParentName="ZPMeleeWeapon">
		<defName>MeleeWeapon_KATANA</defName>
		<label>Katana Blade</label>
		<description>It is a sword handed down in the East. Compared with Longsword, it takes many time and effort to make it, but it has high power.</description>
		<recipeMaker>
			<researchPrerequisite>BlacksmithApprentice</researchPrerequisite>
			<skillRequirements>
				<Crafting>6</Crafting>
			</skillRequirements>
		</recipeMaker>
		<graphicData>
			<texPath>Things/Item/Equipment/WeaponMelee/katana</texPath>
			<graphicClass>Graphic_Single</graphicClass>
			<shaderType>CutoutComplex</shaderType>
		</graphicData>
		<statBases>
			<WorkToMake>35000</WorkToMake>
			<Mass>1.9</Mass>
			<Weapon_Bulk>1.0</Weapon_Bulk>
		</statBases>
		<equippedAngleOffset>-65</equippedAngleOffset>
		<stuffCategories>
			<li>Metallic</li>
			<li>Woody</li>
		</stuffCategories>
		<costStuffCount>120</costStuffCount>
		<tools>
			<li>
				<label>突き</label>
				<capacities>
					<li>Stab</li>
				</capacities>
				<power>15</power>
				<cooldownTime>3</cooldownTime>
			</li>
			<li>
				<label>薙ぎ払い</label>
				<capacities>
					<li>Cut</li>
				</capacities>
				<power>25</power>
				<cooldownTime>3</cooldownTime>
			</li>
			<li>
				<label>振り下ろし</label>
				<capacities>
					<li>Cut</li>
				</capacities>
				<power>30</power>
				<cooldownTime>3</cooldownTime>
			</li>
		</tools>
		<weaponTags>
			<li>ZP_Weapons_Asigaru</li>
		</weaponTags>
	</ThingDef>
	<!-- ================ 大太刀 Base 刀 ================ -->
	<ThingDef ParentName="ZPMeleeWeapon">
		<defName>ZP_Odachi</defName>
		<label>Odachi Blade</label>
		<description>A large sword made for further improvement of power.</description>
		<recipeMaker>
			<researchPrerequisite>BlacksmithArtisan</researchPrerequisite>
			<skillRequirements>
				<Crafting>8</Crafting>
			</skillRequirements>
		</recipeMaker>
		<graphicData>
			<texPath>Things/Item/Equipment/WeaponMelee/ootachi</texPath>
			<graphicClass>Graphic_Single</graphicClass>
			<shaderType>CutoutComplex</shaderType>
		</graphicData>
		<stuffCategories>
			<li>Metallic</li>
			<li>Woody</li>
		</stuffCategories>
		<costStuffCount>200</costStuffCount>
		<statBases>
			<WorkToMake>40000</WorkToMake>
			<Mass>2.2</Mass>
			<Weapon_Bulk>1.5</Weapon_Bulk>
		</statBases>
		<equippedAngleOffset>-65</equippedAngleOffset>
		<tools>
			<li>
				<label>突き</label>
				<capacities>
					<li>Stab</li>
					<li>Cut</li>
				</capacities>
				<power>25</power>
				<cooldownTime>4</cooldownTime>
			</li>
			<li>
				<label>薙ぎ払い</label>
				<capacities>
					<li>Cut</li>
				</capacities>
				<power>30</power>
				<cooldownTime>4</cooldownTime>
			</li>
			<li>
				<label>振り下ろし</label>
				<capacities>
					<li>Cut</li>
				</capacities>
				<power>40</power>
				<cooldownTime>4</cooldownTime>
			</li>
		</tools>
		<weaponTags>
			<li>ZP_Weapons_Syougun</li>
		</weaponTags>
	</ThingDef>
	<!-- ================ 長槍 Base スピア ================ -->
	<ThingDef ParentName="ZPMeleeWeapon">
		<defName>ZP_LongSpear</defName>
		<label>Nagayari Spear</label>
		<description>A weapon with a long reach. Because the reach is long, you can attack from the outside of the opponent's confrontation in the case of proximity battle.</description>
		<recipeMaker>
			<researchPrerequisite>BlacksmithApprentice</researchPrerequisite>
			<skillRequirements>
				<Crafting>6</Crafting>
			</skillRequirements>
		</recipeMaker>
		<graphicData>
			<texPath>Things/Item/Equipment/WeaponMelee/nagaeyari</texPath>
			<graphicClass>Graphic_Single</graphicClass>
			<shaderType>CutoutComplex</shaderType>
		</graphicData>
		<stuffCategories>
			<li>Metallic</li>
			<li>Woody</li>
		</stuffCategories>
		<costStuffCount>80</costStuffCount>
		<statBases>
			<WorkToMake>15000</WorkToMake>
			<Mass>2.2</Mass>
			<Weapon_Bulk>1.5</Weapon_Bulk>
		</statBases>
		<equippedStatOffsets>
			<MeleeDodgeChance>6</MeleeDodgeChance>
		</equippedStatOffsets>
		<equippedAngleOffset>-25</equippedAngleOffset>
		<tools>
			<li>
				<label>殴打</label>
				<capacities>
					<li>Blunt</li>
					<li>Poke</li>
				</capacities>
				<power>15</power>
				<cooldownTime>2</cooldownTime>
			</li>
			<li>
				<label>突き</label>
				<capacities>
					<li>Stab</li>
					<li>Cut</li>
				</capacities>
				<power>23.5</power>
				<cooldownTime>2</cooldownTime>
			</li>
		</tools>
		<weaponTags>
			<li>ZP_Weapons_Asigaru</li>
		</weaponTags>
	</ThingDef>
	<!-- ================ 十文字槍 Base スピア ================ -->
	<ThingDef ParentName="ZPMeleeWeapon">
		<defName>ZP_JumonjiSpear</defName>
		<label>Jumonji Spear</label>
		<description>A weapon with a long reach.It makes the spear tip cross and makes it hard to avoid when piercing. It also has applications such as hooking and scraping.</description>
		<recipeMaker>
			<researchPrerequisite>BlacksmithMaster</researchPrerequisite>
			<skillRequirements>
				<Crafting>8</Crafting>
			</skillRequirements>
		</recipeMaker>
		<graphicData>
			<texPath>Things/Item/Equipment/WeaponMelee/juumonzisou</texPath>
			<graphicClass>Graphic_Single</graphicClass>
			<shaderType>CutoutComplex</shaderType>
		</graphicData>
		<stuffCategories>
			<li>Metallic</li>
			<li>Woody</li>
		</stuffCategories>
		<costStuffCount>150</costStuffCount>
		<statBases>
			<WorkToMake>20000</WorkToMake>
			<Mass>2.2</Mass>
			<Weapon_Bulk>1.5</Weapon_Bulk>
		</statBases>
		<equippedStatOffsets>
			<MeleeHitChance>0.1</MeleeHitChance>
			<MeleeDodgeChance>6</MeleeDodgeChance>
		</equippedStatOffsets>
		<equippedAngleOffset>-25</equippedAngleOffset>
		<tools>
			<li>
				<label>斬り裂き</label>
				<capacities>
					<li>Cut</li>
				</capacities>
				<power>16</power>
				<cooldownTime>2</cooldownTime>
			</li>
			<li>
				<label>殴打</label>
				<capacities>
					<li>Blunt</li>
					<li>Poke</li>
				</capacities>
				<power>22</power>
				<cooldownTime>2</cooldownTime>
			</li>
			<li>
				<label>突き</label>
				<capacities>
					<li>Stab</li>
					<li>Cut</li>
				</capacities>
				<power>28</power>
				<cooldownTime>2</cooldownTime>
			</li>
		</tools>
		<weaponTags>
			<li>ZP_Weapons_Syougun</li>
		</weaponTags>
	</ThingDef>
	<!-- ================ 長槍 Base スピア ================ -->
	<ThingDef ParentName="ZPMeleeWeapon">
		<defName>ZP_Naginata</defName>
		<label>Naginata</label>
		<description>A long stick attached to a sword and improved. It looks like a glaive and has a very long reach</description>
		<recipeMaker>
			<researchPrerequisite>BlacksmithApprentice</researchPrerequisite>
			<skillRequirements>
				<Crafting>6</Crafting>
			</skillRequirements>
		</recipeMaker>
		<graphicData>
			<texPath>Things/Item/Equipment/WeaponMelee/naginata</texPath>
			<graphicClass>Graphic_Single</graphicClass>
			<shaderType>CutoutComplex</shaderType>
		</graphicData>
		<statBases>
			<WorkToMake>15000</WorkToMake>
			<Mass>2.2</Mass>
			<Weapon_Bulk>1.5</Weapon_Bulk>
		</statBases>
		<equippedStatOffsets>
			<MeleeHitChance>0.2</MeleeHitChance>
		</equippedStatOffsets>
		<equippedAngleOffset>-25</equippedAngleOffset>
		<stuffCategories>
			<li>Metallic</li>
			<li>Woody</li>
		</stuffCategories>
		<costStuffCount>80</costStuffCount>
		<tools>
			<li>
				<label>突き</label>
				<capacities>
					<li>Stab</li>
					<li>Cut</li>
				</capacities>
				<power>15</power>
				<cooldownTime>2</cooldownTime>
			</li>
			<li>
				<label>薙ぎ払い</label>
				<capacities>
					<li>Cut</li>
				</capacities>
				<power>20</power>
				<cooldownTime>2</cooldownTime>
			</li>
			<li>
				<label>振り下ろし</label>
				<capacities>
					<li>Cut</li>
				</capacities>
				<power>24</power>
				<cooldownTime>2</cooldownTime>
			</li>
		</tools>
		<weaponTags>
			<li>ZP_Weapons_Asigaru</li>
		</weaponTags>
	</ThingDef>
</Defs>
